quantutils/__init__.py
quantutils/metrics.py
quantutils/plot.py
quantutils-1.3.dist-info/WHEEL
quantutils-1.3.dist-info/METADATA
quantutils-1.3.dist-info/RECORD
