Metadata-Version: 2.1
Name: quantutils
Version: 1.3
Summary: Quant Utils.
Author-email: yvictor <yvictor3141@gmail.com>
Project-URL: Home, https://github.com/Yvictor/quantutil
